sphinxcontrib_httpexample-1.3-py3.7-nspkg.pth
sphinxcontrib/httpexample/__init__.py
sphinxcontrib/httpexample/builders.py
sphinxcontrib/httpexample/directives.py
sphinxcontrib/httpexample/parsers.py
sphinxcontrib/httpexample/utils.py
sphinxcontrib/httpexample/static/sphinxcontrib-httpexample.css
sphinxcontrib/httpexample/static/sphinxcontrib-httpexample.js
sphinxcontrib_httpexample-1.3.dist-info/METADATA
sphinxcontrib_httpexample-1.3.dist-info/WHEEL
sphinxcontrib_httpexample-1.3.dist-info/namespace_packages.txt
sphinxcontrib_httpexample-1.3.dist-info/top_level.txt
sphinxcontrib_httpexample-1.3.dist-info/RECORD
