Metadata-Version: 2.1
Name: sphinxcontrib-httpexample
Version: 1.3
Summary: Adds example directive for sphinx-contrib httpdomain
Home-page: https://github.com/collective/sphinxcontrib-httpexample
Author: Asko Soukka
Author-email: asko.soukka@iki.fi
License: GPL version 2
Keywords: sphinx,extension,http,rest,documentation
Platform: UNKNOWN
Classifier: Development Status :: 5 - Production/Stable
Classifier: Environment :: Console
Classifier: Environment :: Web Environment
Classifier: Framework :: Sphinx :: Extension
Classifier: Intended Audience :: Developers
Classifier: License :: OSI Approved :: GNU General Public License v2 (GPLv2)
Classifier: Operating System :: OS Independent
Classifier: Programming Language :: Python :: 2
Classifier: Programming Language :: Python :: 3
Classifier: Topic :: Documentation
Classifier: Topic :: Utilities
Requires-Dist: astunparse
Requires-Dist: docutils
Requires-Dist: sphinx
Requires-Dist: sphinxcontrib-httpdomain
